Metadata-Version: 2.1
Name: httpsy
Version: 0.3.0
Summary: A simple Python package for sending http request
Classifier: Programming Language :: Python :: 3
Classifier: License :: OSI Approved :: MIT License
Classifier: Operating System :: OS Independent
Requires-Python: >=3.6
